birthdays/__init__.py
birthdays/__version__.py
birthdays/app.py
birthdays/cli.py
birthdays-0.4.4.dist-info/DESCRIPTION.rst
birthdays-0.4.4.dist-info/METADATA
birthdays-0.4.4.dist-info/RECORD
birthdays-0.4.4.dist-info/WHEEL
birthdays-0.4.4.dist-info/entry_points.txt
birthdays-0.4.4.dist-info/metadata.json
birthdays-0.4.4.dist-info/top_level.txt
