Metadata-Version: 2.0
Name: birthdays
Version: 0.4.4
Summary: CLI application to return upcoming birthdays from a textfile.
Home-page: https://github.com/cdrcqnts/birthdays
Author: cdrcqnts
Author-email: cdrcqnts@gmail.com
License: MIT
Platform: UNKNOWN
Classifier: License :: OSI Approved :: MIT License
Classifier: Programming Language :: Python
Classifier: Programming Language :: Python :: 2.6
Classifier: Programming Language :: Python :: 2.7
Classifier: Programming Language :: Python :: 3
Classifier: Programming Language :: Python :: 3.3
Classifier: Programming Language :: Python :: 3.4
Classifier: Programming Language :: Python :: 3.5
Classifier: Programming Language :: Python :: 3.6
Classifier: Programming Language :: Python :: Implementation :: CPython
Classifier: Programming Language :: Python :: Implementation :: PyPy
Requires-Dist: Click
Requires-Dist: datetime
